{
    "116": {
        "G": {
            "espera": 5,
            "atencion": 1
        },
        "H": {
            "espera": 11,
            "atencion": 2
        },
        "AE": {
            "espera": 10,
            "atencion": 1
        },
        "total": {
            "espera": 26,
            "atencion": 4,
            "cola": 30,
            "timestamp": "2025-09-18 12:39:04"
        }
    },
    "Campin": {
        "G": {
            "espera": 1,
            "atencion": 3
        },
        "H": {
            "espera": 1,
            "atencion": 4
        },
        "AE": {
            "espera": 1,
            "atencion": 2
        },
        "total": {
            "espera": 3,
            "atencion": 9,
            "cola": 11,
            "timestamp": "2025-09-18 12:39:04"
        }
    },
    "Kennedy": {
        "F": {
            "espera": 8,
            "atencion": 3
        },
        "M": {
            "espera": 6,
            "atencion": 0
        },
        "total": {
            "espera": 14,
            "atencion": 3,
            "cola": 17,
            "timestamp": "2025-09-18 12:39:04"
        }
    },
    "Occidente": {
        "G": {
            "espera": 2,
            "atencion": 3
        },
        "H": {
            "espera": 6,
            "atencion": 1
        },
        "total": {
            "espera": 8,
            "atencion": 4,
            "cola": 13,
            "timestamp": "2025-09-18 12:39:04"
        }
    }
}