{
    "116": {
        "G": {
            "espera": 19,
            "atencion": 3
        },
        "H": {
            "espera": 12,
            "atencion": 2
        },
        "AE": {
            "espera": 1,
            "atencion": 1
        },
        "total": {
            "espera": 32,
            "atencion": 6,
            "cola": 39,
            "timestamp": "2025-09-29 10:11:29"
        }
    },
    "Campin": {
        "G": {
            "espera": 11,
            "atencion": 3
        },
        "H": {
            "espera": 10,
            "atencion": 3
        },
        "AE": {
            "espera": 2,
            "atencion": 2
        },
        "total": {
            "espera": 23,
            "atencion": 8,
            "cola": 31,
            "timestamp": "2025-09-29 10:11:29"
        }
    },
    "Kennedy": {
        "F": {
            "espera": 0,
            "atencion": 0
        },
        "M": {
            "espera": 0,
            "atencion": 0
        },
        "total": {
            "espera": 0,
            "atencion": 0,
            "cola": 0,
            "timestamp": "2025-09-29 10:11:29"
        }
    },
    "Occidente": {
        "G": {
            "espera": 2,
            "atencion": 1
        },
        "H": {
            "espera": 38,
            "atencion": 2
        },
        "total": {
            "espera": 40,
            "atencion": 3,
            "cola": 43,
            "timestamp": "2025-09-29 10:11:29"
        }
    }
}