{
    "116": {
        "G": {
            "espera": 0,
            "atencion": 0
        },
        "H": {
            "espera": 0,
            "atencion": 0
        },
        "AE": {
            "espera": 0,
            "atencion": 0
        },
        "total": {
            "espera": 0,
            "atencion": 0,
            "cola": 0,
            "timestamp": "2025-11-22 12:25:15"
        }
    },
    "Campin": {
        "G": {
            "espera": 5,
            "atencion": 3
        },
        "H": {
            "espera": 11,
            "atencion": 5
        },
        "AE": {
            "espera": 2,
            "atencion": 2
        },
        "total": {
            "espera": 18,
            "atencion": 10,
            "cola": 28,
            "timestamp": "2025-11-22 12:25:15"
        }
    },
    "Kennedy": {
        "F": {
            "espera": 0,
            "atencion": 0
        },
        "M": {
            "espera": 0,
            "atencion": 0
        },
        "total": {
            "espera": 0,
            "atencion": 0,
            "cola": 0,
            "timestamp": "2025-11-22 12:25:15"
        }
    },
    "Occidente": {
        "G": {
            "espera": 0,
            "atencion": 0
        },
        "H": {
            "espera": 0,
            "atencion": 2
        },
        "total": {
            "espera": 0,
            "atencion": 2,
            "cola": 2,
            "timestamp": "2025-11-22 12:25:15"
        }
    }
}