{
    "116": {
        "G": {
            "espera": 0,
            "atencion": 1
        },
        "H": {
            "espera": 1,
            "atencion": 3
        },
        "AE": {
            "espera": 2,
            "atencion": 3
        },
        "total": {
            "espera": 3,
            "atencion": 7,
            "cola": 10,
            "timestamp": "2025-10-07 14:35:47"
        }
    },
    "Campin": {
        "G": {
            "espera": 2,
            "atencion": 1
        },
        "H": {
            "espera": 2,
            "atencion": 3
        },
        "AE": {
            "espera": 6,
            "atencion": 1
        },
        "total": {
            "espera": 10,
            "atencion": 5,
            "cola": 16,
            "timestamp": "2025-10-07 14:35:47"
        }
    },
    "Kennedy": {
        "F": {
            "espera": 0,
            "atencion": 0
        },
        "M": {
            "espera": 0,
            "atencion": 0
        },
        "total": {
            "espera": 0,
            "atencion": 0,
            "cola": 0,
            "timestamp": "2025-10-07 14:35:47"
        }
    },
    "Occidente": {
        "G": {
            "espera": 1,
            "atencion": 1
        },
        "H": {
            "espera": 38,
            "atencion": 4
        },
        "total": {
            "espera": 39,
            "atencion": 5,
            "cola": 44,
            "timestamp": "2025-10-07 14:35:47"
        }
    }
}