{
    "116": {
        "G": {
            "espera": 8,
            "atencion": 0
        },
        "H": {
            "espera": 12,
            "atencion": 5
        },
        "AE": {
            "espera": 0,
            "atencion": 1
        },
        "total": {
            "espera": 20,
            "atencion": 6,
            "cola": 26,
            "timestamp": "2025-09-19 15:43:39"
        }
    },
    "Campin": {
        "G": {
            "espera": 5,
            "atencion": 5
        },
        "H": {
            "espera": 8,
            "atencion": 5
        },
        "AE": {
            "espera": 8,
            "atencion": 3
        },
        "total": {
            "espera": 21,
            "atencion": 13,
            "cola": 34,
            "timestamp": "2025-09-19 15:43:39"
        }
    },
    "Kennedy": {
        "F": {
            "espera": 0,
            "atencion": 0
        },
        "M": {
            "espera": 0,
            "atencion": 1
        },
        "total": {
            "espera": 0,
            "atencion": 1,
            "cola": 2,
            "timestamp": "2025-09-19 15:43:39"
        }
    },
    "Occidente": {
        "G": {
            "espera": 1,
            "atencion": 3
        },
        "H": {
            "espera": 14,
            "atencion": 2
        },
        "total": {
            "espera": 15,
            "atencion": 5,
            "cola": 20,
            "timestamp": "2025-09-19 15:43:39"
        }
    }
}