{
    "116": {
        "G": {
            "espera": 4,
            "atencion": 2
        },
        "H": {
            "espera": 9,
            "atencion": 3
        },
        "AE": {
            "espera": 3,
            "atencion": 0
        },
        "total": {
            "espera": 16,
            "atencion": 5,
            "cola": 20,
            "timestamp": "2025-09-18 15:10:55"
        }
    },
    "Campin": {
        "G": {
            "espera": 5,
            "atencion": 4
        },
        "H": {
            "espera": 15,
            "atencion": 6
        },
        "AE": {
            "espera": 9,
            "atencion": 3
        },
        "total": {
            "espera": 29,
            "atencion": 13,
            "cola": 41,
            "timestamp": "2025-09-18 15:10:55"
        }
    },
    "Kennedy": {
        "F": {
            "espera": 1,
            "atencion": 1
        },
        "M": {
            "espera": 1,
            "atencion": 1
        },
        "total": {
            "espera": 2,
            "atencion": 2,
            "cola": 5,
            "timestamp": "2025-09-18 15:10:55"
        }
    },
    "Occidente": {
        "G": {
            "espera": 1,
            "atencion": 1
        },
        "H": {
            "espera": 3,
            "atencion": 4
        },
        "total": {
            "espera": 4,
            "atencion": 5,
            "cola": 9,
            "timestamp": "2025-09-18 15:10:55"
        }
    }
}