{
    "116": {
        "G": {
            "espera": 0,
            "atencion": 3
        },
        "H": {
            "espera": 2,
            "atencion": 4
        },
        "AE": {
            "espera": 0,
            "atencion": 0
        },
        "total": {
            "espera": 2,
            "atencion": 7,
            "cola": 9,
            "timestamp": "2025-09-19 07:14:50"
        }
    },
    "Campin": {
        "G": {
            "espera": 1,
            "atencion": 0
        },
        "H": {
            "espera": 3,
            "atencion": 7
        },
        "AE": {
            "espera": 0,
            "atencion": 0
        },
        "total": {
            "espera": 4,
            "atencion": 7,
            "cola": 11,
            "timestamp": "2025-09-19 07:14:50"
        }
    },
    "Kennedy": {
        "F": {
            "espera": 2,
            "atencion": 1
        },
        "M": {
            "espera": 0,
            "atencion": 0
        },
        "total": {
            "espera": 2,
            "atencion": 1,
            "cola": 4,
            "timestamp": "2025-09-19 07:14:50"
        }
    },
    "Occidente": {
        "G": {
            "espera": 0,
            "atencion": 0
        },
        "H": {
            "espera": 8,
            "atencion": 4
        },
        "total": {
            "espera": 8,
            "atencion": 4,
            "cola": 12,
            "timestamp": "2025-09-19 07:14:50"
        }
    }
}