{
    "116": {
        "G": {
            "espera": 1,
            "atencion": 2
        },
        "H": {
            "espera": 0,
            "atencion": 4
        },
        "AE": {
            "espera": 2,
            "atencion": 1
        },
        "total": {
            "espera": 3,
            "atencion": 7,
            "cola": 10,
            "timestamp": "2025-09-22 16:52:54"
        }
    },
    "Campin": {
        "G": {
            "espera": 11,
            "atencion": 2
        },
        "H": {
            "espera": 20,
            "atencion": 4
        },
        "AE": {
            "espera": 12,
            "atencion": 1
        },
        "total": {
            "espera": 43,
            "atencion": 7,
            "cola": 51,
            "timestamp": "2025-09-22 16:52:54"
        }
    },
    "Kennedy": {
        "F": {
            "espera": 30,
            "atencion": 0
        },
        "M": {
            "espera": 19,
            "atencion": 1
        },
        "total": {
            "espera": 49,
            "atencion": 1,
            "cola": 68,
            "timestamp": "2025-09-22 16:52:54"
        }
    },
    "Occidente": {
        "G": {
            "espera": 4,
            "atencion": 1
        },
        "H": {
            "espera": 42,
            "atencion": 3
        },
        "total": {
            "espera": 46,
            "atencion": 4,
            "cola": 51,
            "timestamp": "2025-09-22 16:52:54"
        }
    }
}