{
    "116": {
        "G": {
            "espera": 2,
            "atencion": 1
        },
        "H": {
            "espera": 1,
            "atencion": 4
        },
        "AE": {
            "espera": 9,
            "atencion": 2
        },
        "total": {
            "espera": 12,
            "atencion": 7,
            "cola": 19,
            "timestamp": "2025-10-07 14:01:51"
        }
    },
    "Campin": {
        "G": {
            "espera": 0,
            "atencion": 1
        },
        "H": {
            "espera": 4,
            "atencion": 3
        },
        "AE": {
            "espera": 2,
            "atencion": 3
        },
        "total": {
            "espera": 6,
            "atencion": 7,
            "cola": 13,
            "timestamp": "2025-10-07 14:01:51"
        }
    },
    "Kennedy": {
        "F": {
            "espera": 0,
            "atencion": 0
        },
        "M": {
            "espera": 0,
            "atencion": 0
        },
        "total": {
            "espera": 0,
            "atencion": 0,
            "cola": 0,
            "timestamp": "2025-10-07 14:01:51"
        }
    },
    "Occidente": {
        "G": {
            "espera": 7,
            "atencion": 1
        },
        "H": {
            "espera": 36,
            "atencion": 2
        },
        "total": {
            "espera": 43,
            "atencion": 3,
            "cola": 46,
            "timestamp": "2025-10-07 14:01:51"
        }
    }
}