{
    "116": {
        "G": {
            "espera": 9,
            "atencion": 2
        },
        "H": {
            "espera": 9,
            "atencion": 2
        },
        "AE": {
            "espera": 0,
            "atencion": 0
        },
        "total": {
            "espera": 18,
            "atencion": 4,
            "cola": 23,
            "timestamp": "2025-09-25 07:38:35"
        }
    },
    "Campin": {
        "G": {
            "espera": 0,
            "atencion": 0
        },
        "H": {
            "espera": 0,
            "atencion": 0
        },
        "AE": {
            "espera": 0,
            "atencion": 0
        },
        "total": {
            "espera": 0,
            "atencion": 0,
            "cola": 0,
            "timestamp": "2025-09-25 07:38:35"
        }
    },
    "Kennedy": {
        "F": {
            "espera": 4,
            "atencion": 0
        },
        "M": {
            "espera": 0,
            "atencion": 0
        },
        "total": {
            "espera": 4,
            "atencion": 0,
            "cola": 4,
            "timestamp": "2025-09-25 07:38:35"
        }
    },
    "Occidente": {
        "G": {
            "espera": 4,
            "atencion": 1
        },
        "H": {
            "espera": 10,
            "atencion": 2
        },
        "total": {
            "espera": 14,
            "atencion": 3,
            "cola": 17,
            "timestamp": "2025-09-25 07:38:35"
        }
    }
}