{
    "116": {
        "G": {
            "espera": 16,
            "atencion": 0
        },
        "H": {
            "espera": 9,
            "atencion": 4
        },
        "AE": {
            "espera": 7,
            "atencion": 0
        },
        "total": {
            "espera": 32,
            "atencion": 4,
            "cola": 38,
            "timestamp": "2025-09-23 09:51:18"
        }
    },
    "Campin": {
        "G": {
            "espera": 7,
            "atencion": 2
        },
        "H": {
            "espera": 3,
            "atencion": 2
        },
        "AE": {
            "espera": 20,
            "atencion": 2
        },
        "total": {
            "espera": 30,
            "atencion": 6,
            "cola": 37,
            "timestamp": "2025-09-23 09:51:18"
        }
    },
    "Kennedy": {
        "F": {
            "espera": 6,
            "atencion": 0
        },
        "M": {
            "espera": 7,
            "atencion": 0
        },
        "total": {
            "espera": 13,
            "atencion": 0,
            "cola": 13,
            "timestamp": "2025-09-23 09:51:18"
        }
    },
    "Occidente": {
        "G": {
            "espera": 2,
            "atencion": 1
        },
        "H": {
            "espera": 28,
            "atencion": 2
        },
        "total": {
            "espera": 30,
            "atencion": 3,
            "cola": 33,
            "timestamp": "2025-09-23 09:51:18"
        }
    }
}