{
    "116": {
        "G": {
            "espera": 12,
            "atencion": 0
        },
        "H": {
            "espera": 25,
            "atencion": 2
        },
        "AE": {
            "espera": 1,
            "atencion": 1
        },
        "total": {
            "espera": 38,
            "atencion": 3,
            "cola": 41,
            "timestamp": "2025-10-17 13:30:47"
        }
    },
    "Campin": {
        "G": {
            "espera": 1,
            "atencion": 2
        },
        "H": {
            "espera": 8,
            "atencion": 3
        },
        "AE": {
            "espera": 1,
            "atencion": 3
        },
        "total": {
            "espera": 10,
            "atencion": 8,
            "cola": 18,
            "timestamp": "2025-10-17 13:30:47"
        }
    },
    "Kennedy": {
        "F": {
            "espera": 0,
            "atencion": 0
        },
        "M": {
            "espera": 0,
            "atencion": 0
        },
        "total": {
            "espera": 0,
            "atencion": 0,
            "cola": 0,
            "timestamp": "2025-10-17 13:30:47"
        }
    },
    "Occidente": {
        "G": {
            "espera": 3,
            "atencion": 2
        },
        "H": {
            "espera": 12,
            "atencion": 1
        },
        "total": {
            "espera": 15,
            "atencion": 3,
            "cola": 18,
            "timestamp": "2025-10-17 13:30:47"
        }
    }
}